{"μετα":["MT1_12","MT2_11","MT4_21","MT8_11","MT9_11","MT12_41","MT12_42","MT13_20","MT16_27","MT18_16","MT18_23","MT19_10","MT20_2","MT20_20","MT22_16","MT24_29","MT24_30","MT24_31","MT24_49","MT24_51","MT25_4","MT25_19","MT26_2","MT26_18","MT26_20","MT26_32","MT26_47","MT26_51","MT26_55","MT26_58","MT26_69","MT26_71","MT26_72","MT26_73","MT27_34","MT27_41","MT27_53","MT27_62","MT27_63","MT27_66","MT28_8","MT28_12","MK1_13","MK1_14","MK1_20","MK1_29","MK2_16","MK3_6","MK3_7","MK4_16","MK6_25","MK8_10","MK8_31","MK8_38","MK9_2","MK9_31","MK10_30","MK10_34","MK11_11","MK13_24","MK13_26","MK14_1","MK14_14","MK14_17","MK14_28","MK14_43","MK14_48","MK14_54","MK14_62","MK14_67","MK14_70","MK15_1","MK15_7","MK15_31","MK16_12","MK16_19","MK16_20","LK1_24","LK1_28","LK1_39","LK1_72","LK2_36","LK2_46","LK5_27","LK5_30","LK8_13","LK9_28","LK9_39","LK10_1","LK10_17","LK11_31","LK11_32","LK12_4","LK12_5","LK12_46","LK12_58","LK13_1","LK14_9","LK14_31","LK15_29","LK15_30","LK17_8","LK17_15","LK17_20","LK18_4","LK21_27","LK22_11","LK22_20","LK22_33","LK22_37","LK22_52","LK22_58","LK24_5","LK24_52","JN2_12","JN3_22","JN3_25","JN3_26","JN4_27","JN4_43","JN5_1","JN5_14","JN6_1","JN6_3","JN7_1","JN9_37","JN11_7","JN11_11","JN11_54","JN13_7","JN13_27","JN18_2","JN18_3","JN19_28","JN19_38","JN19_40","JN20_7","JN21_1","AC1_3","AC1_5","AC1_26","AC2_28","AC2_29","AC4_29","AC4_31","AC5_26","AC5_37","AC7_4","AC7_7","AC7_38","AC7_45","AC9_19","AC10_37","AC10_41","AC12_4","AC13_15","AC13_17","AC13_20","AC14_23","AC15_13","AC15_16","AC15_35","AC15_36","AC17_11","AC18_1","AC18_10","AC19_21","AC20_1","AC20_6","AC20_19","AC20_29","AC20_31","AC21_15","AC24_1","AC24_3","AC24_18","AC24_24","AC25_1","AC25_12","AC25_23","AC27_10","AC27_24","AC28_11","AC28_13","AC28_17","AC28_31","RM12_15","RM12_18","RM15_10","RM15_33","C16_6","C111_25","C116_11","C116_12","C116_24","C26_15","C26_16","C27_15","C28_4","C213_13","GL1_18","GL2_1","GL2_12","GL3_17","GL4_25","GL4_30","GL6_18","EP4_2","EP4_25","EP6_5","EP6_23","EP6_24","PP1_4","PP2_12","PP2_29","PP4_3","PP4_6","PP4_23","CL1_11","H11_6","H13_13","H23_12","H23_16","H23_18","T11_14","T12_9","T12_15","T13_4","T14_3","T14_4","T14_14","T16_6","T22_10","T22_22","T24_11","T24_22","TT2_15","TT3_10","TT3_15","PM1_25","HB4_7","HB4_8","HB4_16","HB5_7","HB7_21","HB7_28","HB8_10","HB9_3","HB9_19","HB9_27","HB10_15","HB10_16","HB10_22","HB10_26","HB10_34","HB11_9","HB12_14","HB12_17","HB12_28","HB13_17","HB13_25","P11_11","P13_15","P21_15","J11_3","RV1_7","RV1_19","RV3_21","RV4_1","RV7_1","RV7_9","RV9_12","RV11_11","RV12_7","RV12_17","RV13_7","RV14_4","RV15_5","RV17_12","RV17_14","RV18_1","RV19_1","RV19_19","RV20_3","RV20_4","RV21_3","RV22_21"],"ελεαζαρ":["MT1_15"],"ανηρ":["MT1_19","LK5_8","LK5_12","LK8_27","LK8_38","LK8_41","LK9_38","LK19_2","LK23_50","LK24_19","JN1_30","JN4_18","AC3_2","AC5_1","AC8_9","AC8_27","AC10_1","AC10_22","AC10_30","AC11_24","AC14_8","AC16_9","AC18_24","AC22_3","AC22_12","AC25_14","RM4_8","RM7_2","RM7_3","C17_3","C17_4","C17_14","C17_39","C111_3","C111_4","C111_7","C111_8","C111_9","C111_11","C111_12","C111_14","C113_11","EP5_23","TT1_6","JM1_8","JM1_12","JM2_2","JM3_2"],"δικαιος":["MT1_19","LK2_25","LK23_47","LK23_50","AC10_22","RM1_17","RM3_10","GL3_11","T24_8","HB10_38","HB11_4","P13_18","P14_18","P22_8","J11_9","J12_29","J13_7","RV16_5","RV22_11"],"υιον":["MT1_21","MT1_23","MT1_25","MT2_15","MT10_37","MT11_27","MT16_13","MT16_28","MT17_15","MT21_5","MT21_37","MT21_38","MT23_15","MT24_30","MT26_64","MK8_31","MK9_12","MK9_17","MK12_6","MK13_26","MK14_62","LK1_13","LK1_31","LK1_36","LK1_57","LK2_7","LK3_2","LK9_22","LK9_38","LK9_41","LK12_10","LK20_13","LK20_41","LK21_27","LK22_48","LK24_7","JN1_45","JN1_51","JN3_14","JN3_16","JN3_17","JN3_35","JN3_36","JN4_47","JN5_20","JN5_23","JN6_40","JN6_62","JN8_28","JN9_35","JN12_34","JN17_1","JN19_7","AC7_21","AC7_56","AC13_21","RM8_3","GL1_16","GL4_4","GL4_30","H11_10","HB1_5","HB1_8","HB4_14","HB6_6","HB7_28","HB10_29","HB12_6","JM2_21","J12_22","J12_23","J14_9","J14_10","J14_14","J15_10","J15_12","J21_9","RV1_13","RV12_5","RV14_14"],"εταραχθη":["MT2_3","LK1_12","JN13_21"],"μαγους":["MT2_7"],"μαγων":["MT2_16"],"εθυμωθη":["MT2_16"],"εφοβηθη":["MT2_22","MT14_5","MT14_30","JN19_8","AC22_29"],"ιωαννης":["MT3_1","MT3_4","MT3_14","MT4_12","MT10_2","MT11_2","MT11_18","MT14_2","MT14_4","MT21_32","MK1_4","MK1_6","MK6_14","MK6_18","MK9_38","MK10_35","MK13_3","LK1_60","LK1_63","LK3_16","LK7_19","LK7_20","LK7_33","LK9_7","LK9_49","LK9_54","LK11_1","JN1_6","JN1_15","JN1_26","JN1_28","JN1_32","JN1_35","JN3_23","JN3_24","JN3_27","JN4_1","JN10_40","JN10_41","AC1_5","AC1_13","AC3_1","AC4_6","AC4_19","AC10_37","AC11_16","AC13_13","AC13_25","AC19_4","GL2_9","RV1_4","RV1_9","RV22_8"],"ιορδανη":["MT3_6","MK1_5"],"αγιω":["MT3_11","MT24_15","MK1_8","MK12_36","LK3_16","LK10_21","JN1_33","AC1_5","AC7_51","AC10_38","AC11_16","AC15_28","RM9_1","RM14_17","RM15_16","RM16_16","C112_3","C116_20","C26_6","C213_12","EP1_13","H11_5","H15_26","P11_12","P21_18","JD1_20"],"αχυρον":["MT3_12","LK3_17"],"ωσει":["MT3_16","MT9_36","MT14_21","MK9_26","LK3_23","LK9_14","LK9_28","LK22_41","LK22_44","LK22_59","LK23_44","LK24_11","AC1_15","AC2_3","AC2_41","AC6_15","AC10_3","AC19_7","AC19_34","RM6_13","HB1_12"],"ερχομενον":["MT3_16","MT16_28","MT24_30","MT26_64","MK13_26","MK14_62","MK15_21","LK21_27","LK23_26","JN1_9","JN1_29","JN1_47","JN6_37","JN10_12","AC19_4","HB6_7","J21_7"],"ευδοκησα":["MT3_17","MT17_5","MK1_11","LK3_22","P21_17"],"ποικιλαις":["MT4_24","MK1_34","LK4_40","T23_6","TT3_3","HB2_4","HB13_9"],"καθισαντος":["MT5_1"],"πενθουντες":["MT5_4","RV18_15","RV18_19"],"ειρηνοποιοι":["MT5_9"],"ηλθον":["MT5_17","MT7_25","MT7_27","MT9_13","MT10_34","MT10_35","MT14_34","MT21_1","MK1_29","MK2_17","MK3_8","MK5_1","MK5_14","MK6_29","MK6_53","MK9_33","MK14_16","LK1_59","LK2_44","LK3_12","LK4_42","LK5_7","LK6_18","LK8_35","LK12_49","LK23_33","LK24_1","LK24_23","JN1_31","JN3_26","JN4_40","JN4_45","JN6_24","JN7_45","JN8_14","JN9_39","JN10_8","JN10_10","JN10_41","JN12_9","JN12_27","JN12_47","JN15_22","JN19_32","JN21_8","AC4_23","AC8_36","AC10_29","AC11_12","AC13_13","AC13_51","AC14_24","AC17_1","AC17_13","AC22_11","AC28_23","C12_1","C21_23","GL1_21","GL2_12","RV7_13"],"μια":["MT5_18","MT19_6","MT24_41","MT26_69","MK10_8","MK12_42","MK14_66","MK16_2","LK5_12","LK5_17","LK8_22","LK13_10","LK17_35","LK20_1","LK24_1","JN10_16","JN20_1","JN20_19","AC4_32","AC19_34","AC20_7","C110_8","GL4_24","EP4_4","EP4_5","PP1_27","HB10_14","P23_8","RV9_12","RV18_8","RV18_10","RV18_17","RV18_19"],"λυση":["MT5_19","J13_8"],"εσται":["MT5_21","MT5_22","MT6_21","MT6_22","MT6_23","MT8_12","MT10_15","MT11_22","MT11_24","MT12_11","MT12_40","MT12_45","MT13_40","MT13_42","MT13_49","MT13_50","MT16_19","MT16_22","MT18_18","MT19_27","MT20_26","MT20_27","MT22_13","MT22_28","MT23_11","MT24_3","MT24_21","MT24_27","MT24_37","MT24_39","MT24_51","MT25_30","MT27_64","MK9_35","MK10_43","MK10_44","MK11_23","MK11_24","MK12_7","MK12_23","MK13_4","MK14_2","LK1_14","LK1_15","LK1_32","LK1_33","LK1_34","LK1_45","LK1_66","LK2_10","LK3_5","LK4_7","LK6_35","LK6_40","LK10_12","LK10_14","LK11_30","LK11_36","LK12_20","LK12_34","LK12_55","LK13_28","LK14_10","LK15_7","LK17_24","LK17_26","LK17_30","LK17_31","LK19_46","LK21_7","LK21_11","LK21_23","LK21_24","LK22_69","JN12_26","JN14_17","JN19_24","AC2_17","AC2_21","AC3_23","AC7_6","AC27_22","AC27_25","RM4_18","RM9_9","RM9_26","RM15_12","C111_27","C23_8","C211_15","C213_11","PP4_9","CL2_8","T22_21","T23_9","T24_3","HB1_5","HB3_12","JM1_25","JM5_3","J21_2","J21_3","RV10_6","RV10_9","RV21_3","RV21_4","RV21_7","RV21_25","RV22_3","RV22_5","RV22_14"],"δωρον":["MT5_23","MT5_24","MT8_4","MT15_5","MT23_19","MK7_11","EP2_8"],"θυσιαστηριου":["MT5_24","MT23_35","LK1_11","LK11_51","C110_18","RV6_9","RV8_3","RV8_5","RV9_13","RV14_18","RV16_7"],"οφθαλμος":["MT5_29","MT6_22","MT6_23","MT18_9","MT20_15","MK7_22","MK9_47","LK11_34","C12_9","C112_16","C112_17","C112_21","RV1_7"],"παρεκτος":["MT5_32","AC26_29","C211_28"],"ποιει":["MT5_32","MT6_3","MT7_17","MT7_24","MT8_9","MT13_23","MT26_73","MK3_8","MK4_32","MK7_37","LK7_8","LK10_28","LK10_37","JN4_1","JN5_19","JN5_20","JN7_4","JN7_19","JN7_51","JN11_47","JN14_10","JN15_15","RM13_3","C17_38","J13_4","J13_9","J31_10","RV13_12","RV13_13","RV13_16"],"επιορκησεις":["MT5_33"],"πονηρους":["MT5_45","MT7_17","MT7_18","MT13_49","MT22_10","LK6_35","AC17_5"],"αγαπωντας":["MT5_46","LK6_32"],"υποκριται":["MT6_2","MT6_5","MT6_16","MT15_7","MT22_18","MT23_13","MT23_15","MT23_23","MT23_25","MT23_27","MT23_29","LK12_56","LK13_15"],"αιτησαι":["MT6_8"],"εισενεγκης":["MT6_13","LK11_4"],"ημας":["MT6_13","MT8_29","MT8_31","MT9_27","MT13_56","MT17_4","MT20_7","MT20_30","MT20_31","MT27_4","MT27_25","MK1_24","MK5_12","MK6_3","MK9_5","MK9_22","LK1_71","LK1_78","LK4_34","LK7_20","LK9_33","LK11_1","LK11_4","LK11_45","LK12_41","LK16_26","LK17_13","LK19_14","LK20_6","LK20_22","LK23_15","LK23_30","LK23_39","LK24_22","JN1_22","JN9_4","JN9_34","AC1_21","AC3_4","AC4_12","AC5_28","AC6_2","AC7_40","AC11_15","AC14_11","AC14_22","AC16_10","AC16_15","AC16_37","AC20_5","AC21_1","AC21_5","AC21_11","AC21_17","AC27_1","AC27_6","AC27_7","AC27_20","AC27_26","AC28_2","AC28_7","AC28_10","RM3_8","RM4_24","RM5_8","RM6_6","RM7_6","RM8_18","RM8_35","RM8_37","RM8_39","RM9_24","RM15_7","C14_1","C14_9","C16_14","C18_8","C19_10","C110_6","C21_4","C21_5","C21_8","C21_10","C21_11","C21_14","C21_21","C21_22","C22_14","C23_6","C24_14","C25_5","C25_10","C25_14","C25_18","C27_2","C27_6","C28_6","C28_20","C210_2","GL1_4","GL1_23","GL2_4","GL3_13","GL5_1","EP1_3","EP1_4","EP1_5","EP1_6","EP1_8","EP1_12","EP1_19","EP2_4","EP2_5","EP2_7","EP5_2","PP3_17","CL1_13","H11_8","H11_10","H12_15","H12_16","H12_18","H13_6","H14_7","H15_9","H21_4","H22_16","H23_7","H23_9","T21_9","T22_12","TT2_12","TT2_14","TT3_5","TT3_6","TT3_15","HB2_1","HB2_3","HB13_6","JM1_18","P11_3","P21_3","J11_7","J11_9","J13_1","J14_10","J14_11","J14_19","J31_9","J31_10","RV1_5","RV1_6","RV6_16"],"παραπτωματα":["MT6_14","MT6_15","MK11_25","RM4_25","C25_19","CL2_13"],"βρωσις":["MT6_19","MT6_20","JN6_55","RM14_17"],"φωτεινον":["MT6_22","LK11_34","LK11_36"],"συναγουσιν":["MT6_26","JN15_6"],"βλεπεις":["MT7_3","MT22_16","MK5_31","MK8_23","MK12_14","MK13_2","LK6_41","LK7_44","JM2_22","RV1_11"],"ερεις":["MT7_4","AC23_5","RM9_19","RM11_19","TT3_9"],"ιχθυν":["MT7_10","MT17_27","LK11_11"],"αγαθα":["MT7_11","MT12_34","MT12_35","LK11_13","LK12_18","LK12_19","LK16_25","JN5_29","RM3_8","RM10_15"],"ποιωσιν":["MT7_12","LK6_31","RM2_14","HB13_17"],"επροφητευσαμεν":["MT7_22"],"εγενετο":["MT7_28","MT8_24","MT8_26","MT9_10","MT11_1","MT11_26","MT13_53","MT17_2","MT19_1","MT21_42","MT26_1","MT27_45","MT28_2","MK1_4","MK1_9","MK1_11","MK2_23","MK2_27","MK4_4","MK4_10","MK4_22","MK4_39","MK5_16","MK6_14","MK9_3","MK9_7","MK9_26","MK11_19","MK12_11","MK15_33","LK1_5","LK1_8","LK1_23","LK1_41","LK1_44","LK1_59","LK1_65","LK2_1","LK2_2","LK2_6","LK2_13","LK2_15","LK2_42","LK2_46","LK3_2","LK3_21","LK4_25","LK4_36","LK5_1","LK5_12","LK5_17","LK6_1","LK6_6","LK6_12","LK6_13","LK6_16","LK6_49","LK7_11","LK8_1","LK8_22","LK8_24","LK9_18","LK9_28","LK9_29","LK9_33","LK9_34","LK9_35","LK9_37","LK9_51","LK10_21","LK11_1","LK11_14","LK11_27","LK11_30","LK13_19","LK14_1","LK15_14","LK16_22","LK17_11","LK17_14","LK17_26","LK17_28","LK18_35","LK19_9","LK19_15","LK19_29","LK20_1","LK22_14","LK22_24","LK22_44","LK22_66","LK23_44","LK24_4","LK24_15","LK24_19","LK24_21","LK24_30","LK24_31","LK24_51","JN1_3","JN1_6","JN1_10","JN1_14","JN1_17","JN1_28","JN2_1","JN3_25","JN5_9","JN6_16","JN6_21","JN7_43","JN10_19","JN10_22","JN10_35","JN19_36","AC1_19","AC2_2","AC4_5","AC5_5","AC5_7","AC5_11","AC6_1","AC7_13","AC7_29","AC7_31","AC7_40","AC8_1","AC8_8","AC9_3","AC9_19","AC9_32","AC9_37","AC9_42","AC9_43","AC10_10","AC10_13","AC10_16","AC10_25","AC11_10","AC11_26","AC11_28","AC12_18","AC14_1","AC14_5","AC15_39","AC16_16","AC16_26","AC19_1","AC19_10","AC19_17","AC19_23","AC19_34","AC20_3","AC20_37","AC21_1","AC21_5","AC21_30","AC21_35","AC22_6","AC22_17","AC23_7","AC23_9","AC27_27","AC27_39","AC27_42","AC27_44","AC28_8","AC28_17","RM7_13","RM11_34","C115_45","C21_19","H13_4","T23_9","T23_11","HB2_2","HB5_9","HB11_7","RV2_8","RV6_12","RV8_1","RV8_7","RV8_8","RV8_11","RV11_13","RV11_15","RV12_7","RV12_10","RV16_2","RV16_3","RV16_4","RV16_10","RV16_18","RV16_19","RV18_2"],"μηδενι":["MT8_4","MT16_20","MT17_9","MK1_44","MK7_36","MK8_30","MK9_9","LK5_14","LK8_56","LK9_21","AC4_17","AC11_19","AC23_22","RM12_17","RM13_8","C11_7","C26_3","C27_9","PP1_28","T15_22","JM1_4"],"εισελθης":["MT8_8","MK8_26","MK9_25","LK7_6"],"πορευθητι":["MT8_9","LK7_8","AC9_11","AC28_26"],"μαθητων":["MT8_21","MT11_2","MT26_18","MT26_20","MK3_7","MK7_2","MK8_10","MK10_46","MK11_1","MK13_1","MK14_13","MK14_14","LK6_17","LK7_19","LK9_40","LK11_1","LK19_29","LK19_37","LK22_11","JN1_35","JN3_25","JN6_3","JN6_8","JN6_60","JN6_66","JN11_54","JN12_4","JN13_5","JN13_23","JN16_17","JN18_2","JN18_17","JN18_19","JN18_25","JN20_30","JN21_2","JN21_12","AC6_1","AC6_2","AC6_7","AC9_19","AC11_29","AC14_20","AC14_22","AC15_10","AC21_16"],"θαλασση":["MT8_24","MT8_26","MK1_16","MK4_1","MK4_39","MK5_13","LK17_6","AC7_36","C110_2","C211_26","RV8_9","RV16_3","RV18_19"],"δαιμονιζομενοι":["MT8_28"],"βοσκομενη":["MT8_30","MK5_11","LK8_32"],"εξελθοντες":["MT8_32","MT9_31","MT12_14","MT22_10","MT27_53","MK1_29","MK3_6","MK6_12","MK9_30","MK16_20","LK10_10","AC12_10","AC15_24","AC16_36","AC16_40","AC21_5","AC21_8","HB3_16"],"διεπερασεν":["MT9_1"],"περιπατει":["MT9_5","MK2_9","LK5_23","JN5_8","JN5_11","JN5_12","AC3_6","EP4_17","P15_8","J12_11"],"ειδητε":["MT9_6","MK2_10","LK5_24","EP6_21","J12_29","J15_13"],"ελεος":["MT9_13","MT12_7","MT23_23","LK1_50","LK1_58","LK1_72","LK10_37","GL6_16","T11_2","T21_2","T21_16","T21_18","TT3_5","HB4_16","JM2_13","P11_3","J21_3","JD1_2","JD1_21"],"πολλα":["MT9_14","MT13_3","MT16_21","MT19_22","MT27_19","MT27_52","MK1_34","MK1_45","MK3_12","MK4_2","MK5_10","MK5_23","MK5_26","MK5_38","MK5_43","MK6_13","MK6_20","MK6_23","MK6_34","MK7_4","MK7_13","MK8_31","MK9_12","MK9_26","MK10_22","MK12_41","MK15_3","LK3_18","LK8_30","LK9_22","LK10_41","LK12_19","LK17_25","LK22_65","JN3_23","JN8_26","JN10_32","JN11_47","JN14_30","JN16_12","JN20_30","JN21_25","AC2_43","AC5_12","AC25_7","AC26_9","AC26_24","RM12_4","RM15_22","RM16_6","RM16_12","C112_12","C112_14","C112_20","C116_12","C116_19","GL4_27","T24_14","JM3_2","J21_12","J31_13","RV8_3","RV19_12"],"δυνανται":["MT9_15","MK2_19","LK20_36","AC24_13","RM8_8","T15_25","HB10_1","HB10_11","RV9_20"],"απαρθη":["MT9_15","MK2_20","LK5_35"],"ασκοι":["MT9_17","MK2_22","LK5_37"],"εκχειται":["MT9_17"],"εαυτη":["MT9_21","AC7_21"],"αρχοντος":["MT9_23"],"απεθανεν":["MT9_24","MT22_27","MK5_35","MK5_39","MK9_26","MK12_21","MK12_22","MK15_44","LK8_52","LK8_53","LK16_22","LK20_29","LK20_32","JN8_52","JN8_53","JN11_14","JN11_21","JN11_32","RM5_6","RM5_8","RM6_10","RM14_9","RM14_15","C18_11","C115_3","C25_14","C25_15","GL2_21","H14_14","P13_18","RV8_9","RV16_3"],"ερριμμενοι":["MT9_36"],"πηραν":["MT10_10","MK6_8","LK9_3","LK10_4","LK22_36"],"ελθατω":["MT10_13"],"πολεως":["MT10_14","MT21_17","MT23_34","MK11_19","LK2_4","LK4_29","LK7_12","LK8_27","LK9_5","LK10_11","LK14_21","LK23_51","JN1_44","JN4_30","JN4_39","JN19_20","AC7_58","AC13_50","AC14_4","AC14_13","AC14_19","AC16_14","AC16_39","AC21_5","AC21_39","AC25_23","RM16_23","RV3_12","RV11_8","RV11_13","RV14_20","RV21_14","RV21_19","RV21_21","RV22_19"],"κυριος":["MT10_25","MT12_8","MT18_25","MT18_27","MT18_32","MT18_34","MT20_8","MT21_3","MT21_40","MT22_44","MT24_42","MT24_45","MT24_46","MT24_48","MT24_50","MT25_19","MT25_21","MT25_23","MT25_26","MT27_10","MK2_28","MK5_19","MK11_3","MK12_9","MK12_29","MK12_36","MK13_20","MK13_35","MK16_19","LK1_25","LK1_28","LK1_32","LK1_58","LK1_68","LK2_11","LK2_15","LK6_5","LK7_13","LK10_1","LK10_41","LK11_39","LK12_37","LK12_42","LK12_43","LK12_45","LK12_46","LK13_15","LK14_23","LK16_3","LK16_8","LK17_6","LK18_6","LK19_31","LK19_34","LK20_13","LK20_15","LK20_42","LK22_61","LK24_34","JN4_1","JN13_13","JN13_14","JN15_15","JN20_28","JN21_7","JN21_12","AC1_21","AC2_34","AC2_39","AC2_47","AC3_22","AC7_33","AC7_49","AC9_10","AC9_11","AC9_15","AC9_17","AC10_36","AC12_11","AC12_17","AC13_47","AC15_17","AC16_14","AC17_24","AC18_9","AC22_10","AC23_11","AC26_15","RM4_8","RM9_28","RM9_29","RM10_9","RM10_12","RM12_19","RM14_4","RM14_11","C13_5","C13_20","C14_4","C14_5","C14_19","C16_13","C17_10","C17_12","C17_17","C18_6","C19_14","C111_23","C112_3","C112_5","C114_21","C116_7","C23_17","C26_17","C26_18","C210_8","C210_18","C213_10","GL4_1","EP4_5","EP6_9","PP2_11","PP4_5","CL3_13","H13_11","H13_12","H14_6","H14_16","H22_8","H22_16","H23_3","H23_5","H23_16","T16_15","T21_16","T21_18","T22_7","T22_19","T23_11","T24_8","T24_14","T24_17","T24_18","T24_22","HB7_14","HB7_21","HB8_2","HB8_8","HB8_9","HB8_10","HB10_16","HB10_30","HB12_6","HB13_6","JM4_15","JM5_11","JM5_15","P12_3","P21_14","P22_9","P23_9","JD1_5","JD1_9","JD1_14","RV1_8","RV4_8","RV4_11","RV11_8","RV17_14","RV18_8","RV19_6","RV19_16","RV21_22","RV22_5","RV22_6"],"ασσαριου":["MT10_29"],"διχασαι":["MT10_35"],"εμε":["MT10_37","MT10_40","MT18_5","MT18_6","MT18_21","MT26_10","MT26_11","MK9_37","MK9_42","MK14_7","LK1_43","LK4_18","LK9_48","LK10_16","LK22_53","LK23_28","LK24_39","JN3_30","JN6_35","JN6_37","JN6_45","JN6_57","JN7_7","JN7_38","JN8_19","JN8_42","JN10_32","JN11_25","JN11_26","JN12_8","JN12_30","JN12_44","JN12_45","JN12_46","JN12_48","JN13_18","JN13_20","JN14_1","JN14_9","JN14_12","JN15_18","JN15_20","JN15_23","JN15_24","JN16_3","JN16_9","JN16_14","JN16_23","JN16_27","JN17_18","JN17_20","JN17_23","JN18_8","AC3_22","AC7_37","AC8_24","AC13_25","AC22_6","AC22_8","AC22_13","AC23_22","AC24_19","AC26_18","RM1_15","RM10_20","RM15_3","C19_3","C115_10","C22_5","C211_10","C212_6","C212_9","EP6_21","PP1_12","PP2_23","PP2_27","CL4_7","T21_8","PM1_17","RV1_17"],"σταυρον":["MT10_38","MT16_24","MT27_32","MK8_34","MK15_21","LK9_23","LK14_27","LK23_26","JN19_17","HB12_2"],"αναβλεπουσιν":["MT11_5","LK7_22"],"σαλευομενον":["MT11_7","LK7_24"],"μειζων":["MT11_11","MT18_1","MT18_4","MT23_11","MT23_17","MK9_34","MK12_31","LK7_28","LK9_46","LK22_24","LK22_26","LK22_27","JN4_12","JN8_53","JN13_16","JN14_28","JN15_20","RM9_12","C113_13","C114_5","J13_20","J14_4","J15_9"],"εδικαιωθη":["MT11_19","LK7_35","RM4_2","T13_16","JM2_21","JM2_25"],"σοφων":["MT11_25","LK10_21","C11_19","C13_20"],"φανερον":["MT12_16","MK3_12","MK4_22","MK6_14","LK8_17","AC4_16","AC7_13","RM1_19","C13_13"],"ελπιουσιν":["MT12_21","RM15_12"],"λαλειν":["MT12_22","MT12_34","MK1_34","MK7_37","MK12_1","LK4_41","LK7_15","JN8_26","AC2_4","AC4_17","AC4_20","AC4_29","AC5_40","AC11_15","RM15_18","C114_5","C114_34","C114_35","C114_39","PP1_14","H11_8"],"εμερισθη":["MT12_26","MK3_26"],"γινωσκεται":["MT12_33","LK6_44"],"εξελθη":["MT12_43","LK11_24","RV3_12"],"αδελφη":["MT12_50","MK3_35","LK10_39","LK10_40","JN11_39","JN19_25","C17_15","PM1_2","JM2_15"],"εκαθητο":["MT13_1","MT15_29","MT26_58","MT26_69","MT28_2","MK3_32","MK10_46","LK18_35","LK22_55","JN6_3","AC14_8"],"αιγιαλον":["MT13_2","MT13_48","JN21_4","AC21_5","AC27_39","AC27_40"],"ακουοντες":["MT13_13","MK3_8","MK4_12","MK6_2","LK2_47","LK4_28","LK8_10","LK8_21","LK11_28","AC7_54","AC9_7","AC9_21","AC18_8","GL1_23","RV1_3"],"ηκουσαν":["MT13_15","MT13_17","MK11_18","LK1_58","LK2_20","LK10_24","JN1_37","JN4_1","JN7_32","JN9_40","JN10_8","JN12_18","AC5_24","AC11_1","AC22_9","AC28_27","RM10_14","RM10_18","RV11_12"],"ιασομαι":["MT13_15","JN12_40","AC28_27"],"σπερμα":["MT13_24","MT13_27","MT13_37","MT13_38","MT22_24","MT22_25","MK12_19","MK12_20","MK12_21","MK12_22","LK20_28","JN8_33","JN8_37","AC7_6","RM4_18","RM9_7","RM9_8","RM9_29","C29_10","C211_22","GL3_19","GL3_29","HB11_18","J13_9"],"κατασκηνουν":["MT13_32","MK4_32"],"ζιζανιων":["MT13_36"],"αγρος":["MT13_38","MT27_8"],"εμπορω":["MT13_45"],"σαγηνη":["MT13_47"],"σαπρα":["MT13_48"],"καινα":["MT13_52","C25_17","RV21_5"],"προφητης":["MT13_57","MT21_11","MK6_4","MK6_15","MK11_32","LK1_76","LK4_24","LK7_16","LK7_39","LK9_8","LK9_19","LK24_19","JN1_21","JN1_23","JN1_25","JN4_19","JN4_44","JN6_14","JN7_40","JN7_52","JN9_17","AC2_30","AC7_48","AC8_34","AC21_10","C114_37","TT1_12"],"ηραν":["MT14_12","MT14_20","MT15_37","MK6_29","MK6_43","MK8_8","LK17_13","JN8_59","JN11_41","JN20_2","JN20_13","AC4_24"],"πτωμα":["MT14_12","MT24_28","MK6_29","MK15_45","RV11_8","RV11_9"],"απολυσας":["MT14_23","MT15_39"],"αληθως":["MT14_33","MT26_73","MT27_54","MK14_70","MK15_39","LK9_27","LK12_44","LK21_3","JN1_47","JN4_42","JN6_14","JN7_26","JN7_40","JN8_31","JN17_8","AC12_11","H12_13","J12_5"],"οσοι":["MT14_36","MK3_10","MK6_56","LK4_40","LK9_5","JN1_12","JN10_8","AC3_24","AC4_6","AC4_34","AC5_36","AC5_37","AC10_45","AC13_48","RM2_12","RM6_3","RM8_14","GL3_10","GL3_27","GL6_12","GL6_16","PP3_15","CL2_1","T16_1","HB2_15","RV2_24","RV13_15","RV18_17"],"παραβαινετε":["MT15_3"],"εκπορευομενον":["MT15_11","MK7_20","RV22_1"],"φονοι":["MT15_19","MK7_21"],"τυρου":["MT15_21","MK7_24","MK7_31","LK6_17","AC21_7"],"χαναναια":["MT15_22"],"ερριψαν":["MT15_30","AC27_19"],"ποδας":["MT15_30","MT18_8","MT22_13","MT28_9","MK5_22","MK7_25","MK9_45","LK1_79","LK7_38","LK7_44","LK7_45","LK7_46","LK8_35","LK8_41","LK10_11","LK10_39","LK15_22","LK17_16","LK24_39","LK24_40","JN11_2","JN11_32","JN11_44","JN12_3","JN13_5","JN13_6","JN13_8","JN13_9","JN13_10","JN13_12","JN13_14","AC4_35","AC4_37","AC5_2","AC5_10","AC7_58","AC10_25","AC14_10","AC16_24","AC21_11","AC22_3","AC26_16","RM16_20","C115_25","C115_27","EP1_22","EP6_15","T15_10","RV1_17","RV11_11"],"διδαχης":["MT16_12","JN7_17","JN18_19","AC5_28","RM6_17","HB6_2"],"ανταλλαγμα":["MT16_26","MK8_37"],"πραξιν":["MT16_27","RM12_4"],"συλλαλουντες":["MT17_3","MK9_4"],"πασχειν":["MT17_12","PP1_29","P13_17","RV2_10"],"σεληνιαζεται":["MT17_15"],"σκανδαλισωμεν":["MT17_27"],"σκανδαλιση":["MT18_6","MK9_42","MK9_43","LK17_2"],"ευρειν":["MT18_13","AC7_46","AC19_1","C22_13","T21_18"],"ελεγξον":["MT18_15","T24_2"],"αφησω":["MT18_21","JN14_18"],"ηλεησα":["MT18_33"],"ενεκα":["MT19_5","LK6_22","AC19_32","AC26_21"],"γυναικι":["MT19_5","MT26_10","JN4_42","AC5_1","AC24_24","C17_3","C17_14","C17_27","C17_33","C111_6","C114_35","T12_12","RV12_14","RV12_16","RV12_17"],"χωρουσιν":["MT19_11"],"οις":["MT19_11","MT20_23","MK10_40","LK1_78","LK2_20","LK9_43","LK12_1","LK12_24","LK19_15","LK24_25","AC1_3","AC2_22","AC11_14","AC15_24","AC17_34","AC20_25","AC26_12","AC28_23","RM1_6","RM4_24","RM6_21","RM15_21","RM16_4","C22_16","C24_4","GL2_5","GL3_1","GL4_9","EP2_3","EP2_10","PP2_15","PP4_11","CL1_27","CL3_7","T23_14","HB6_18","HB13_9","P11_12","P22_3","P22_12","P22_17","P23_13","JD1_13","RV7_2","RV19_20"],"ευνουχοι":["MT19_12"],"πωλησον":["MT19_21","MK10_21","LK18_22"],"πτωχοις":["MT19_21","MT26_9","MK10_21","MK14_5","LK4_18","LK18_22","LK19_8","JN12_5","JN13_29"],"ραφιδος":["MT19_24","MK10_25"],"εκατονταπλασιονα":["MT19_29","MK10_30","LK8_8"],"μισθωσασθαι":["MT20_1"],"ενδεκατην":["MT20_6","MT20_9"],"εσχατων":["MT20_8","P23_3","RV21_9"],"αναβαινων":["MT20_17","MK1_10","LK19_28","JN10_1"],"αιτουσα":["MT20_20"],"δεξιων":["MT20_21","MT20_23","MT22_44","MT25_33","MT25_34","MT26_64","MT27_38","MK10_37","MK10_40","MK12_36","MK14_62","MK15_27","MK16_19","LK1_11","LK20_42","LK22_69","LK23_33","AC2_25","AC2_34","AC7_55","AC7_56","C26_7","HB1_13"],"στας":["MT20_32","MK10_49"],"αγοραζοντας":["MT21_12","MK11_15"],"καιρος":["MT21_34","MT26_18","MK1_15","MK11_13","MK13_33","LK21_8","JN7_6","JN7_8","C17_29","C26_2","T24_3","T24_6","P14_17","RV1_3","RV11_18","RV22_10"],"εκδωσεται":["MT21_41"],"απεδοκιμασαν":["MT21_42","MK12_10","LK20_17","P12_7"],"λικμησει":["MT21_44","LK20_18"],"γαμους":["MT22_2","MT22_3","MT22_4","MT22_9","MT25_10","LK14_8"],"εκεινοι":["MT22_10","MK4_20","MK12_7","MK16_20","LK12_37","LK12_38","LK13_4","JN7_45","JN10_6","JN11_13","JN19_15","JN20_13","AC21_6","C19_25","C115_11","HB12_25"],"ενδεδυμενον":["MT22_11","RV1_13"],"εισηλθες":["MT22_12","AC11_3"],"καισαρι":["MT22_17","MT22_21","MK12_14","MK12_17","LK20_22","LK20_25","LK23_2","JN19_12","AC27_24"],"επηρωτησεν":["MT22_35","MT22_41","MT27_11","MK9_16","MK9_21","MK12_28","MK14_60","MK15_2","MK15_44","LK8_30","LK9_18","LK18_18","LK18_40","LK23_6","JN18_7","AC5_27"],"ταπεινωθησεται":["MT23_12","LK3_5","LK14_11","LK18_14"],"προσηλυτον":["MT23_15","AC6_5"],"αφηκατε":["MT23_23"],"κωνωπα":["MT23_24"],"εξωθεν":["MT23_25","MT23_27","MT23_28","MK7_15","MK7_18","LK11_39","LK11_40","C27_5","T13_7","P13_3","RV11_2","RV14_20"],"φαινεσθε":["MT23_28","PP2_15"],"σοφους":["MT23_34","RM16_19","C11_27","C13_19"],"φευγετωσαν":["MT24_16","MK13_14","LK21_21"],"κακος":["MT24_48"],"ευ":["MT25_21","MT25_23","MK14_7","AC15_29","EP6_3"],"θεριζω":["MT25_26"],"πεινωντα":["MT25_37","MT25_44"],"κατηραμενοι":["MT25_41"],"βαρυτιμου":["MT26_7"],"κατεχεεν":["MT26_7","MK14_3"],"δους":["MT26_26","MK13_34","LK20_2","AC9_41","AC15_8","RM4_20","C112_24","C21_22","C25_5","H22_16","T12_6"],"αφειλεν":["MT26_51","MK14_47","LK22_50"],"παραστησει":["MT26_53","C18_8","C24_14"],"προφητευσον":["MT26_68","MK14_65","LK22_64"],"εμπτυσαντες":["MT27_30"],"εξεδυσαν":["MT27_31","MK15_20"],"κρανιου":["MT27_33","MK15_22","JN19_17"],"χολης":["MT27_34"],"καταλυων":["MT27_40","MK15_29"],"οικοδομων":["MT27_40","MK15_29","AC4_11"],"εβοησεν":["MT27_46","MK15_34","LK9_38","LK18_38"],"φωνει":["MT27_47","MK10_49","MK15_35","LK14_12","JN2_9","JN10_3","JN11_28"],"εμαθητευθη":["MT27_57"],"μεγαν":["MT27_60","MK4_41","LK2_9","AC8_2","AC8_9","HB4_14","HB10_21","HB13_20","RV12_12","RV14_19","RV16_12","RV18_21","RV20_11"],"εσταυρωμενον":["MT28_5","MK16_6","C11_23","C12_2"],"προαγει":["MT28_7","MK16_7"],"αυταις":["MT28_9","MT28_10","MK16_6","LK8_3","LK13_14","LK24_4","LK24_10","LK24_11","JN5_39","C114_34","PP4_3","T11_18","T15_16","HB10_1","HB10_3","P23_16","RV9_3","RV9_4","RV9_5","RV9_19","RV15_1"],"ικανα":["MT28_12"],"ευαγγελιου":["MK1_1","MK8_35","MK10_29","AC15_7","C14_15","C19_14","C24_4","GL2_5","GL2_14","EP3_6","EP6_15","EP6_19","PP1_7","PP1_12","PP1_16","PP1_27","PP4_15","CL1_5","CL1_23","H22_14","T21_10","PM1_13"],"κυψας":["MK1_7","JN8_6"],"υποδηματων":["MK1_7","LK3_16","LK22_35"],"σπαραξαν":["MK1_26"],"επιραπτει":["MK2_21"],"παλαιον":["MK2_21","LK5_36","LK5_39","EP4_22","CL3_9"],"εξεστη":["MK3_21"],"αλλο":["MK4_5","MK4_7","JN6_22","AC19_32","AC21_34","GL1_7","GL5_10","RV2_24","RV12_3","RV13_11","RV15_1","RV20_12"],"ισχυεν":["MK5_4","AC19_20"],"λιθοις":["MK5_5","LK21_5","C23_7"],"εσμεν":["MK5_9","LK9_12","LK17_10","JN8_33","JN9_28","JN9_40","JN10_30","AC2_32","AC3_15","AC5_32","AC14_15","AC16_28","AC17_28","AC23_15","RM6_15","RM8_12","RM8_16","RM12_5","RM14_8","C13_9","C110_17","C110_22","C115_19","C21_14","C21_24","C22_15","C22_17","C23_5","C26_16","C210_11","C213_6","GL3_25","GL4_28","GL4_31","EP2_10","EP4_25","EP5_30","PP3_3","H15_5","HB3_6","HB4_2","HB10_10","HB10_39","J12_5","J13_1","J13_2","J13_19","J14_6","J14_17","J15_19","J15_20"],"περιεβλεπετο":["MK5_32"],"κλαιοντας":["MK5_38","JN11_33"],"ταλιθα":["MK5_41"],"κουμ":["MK5_41"],"παρηγγειλεν":["MK6_8","LK5_14","LK8_29","LK8_56","LK9_21","AC1_4","AC10_42"],"εξαυτης":["MK6_25","AC10_33","AC11_11","AC21_32","AC23_30","PP2_23"],"ενεγκαι":["MK6_27"],"πασων":["MK6_33","LK19_37","AC7_10","C28_18","C211_28"],"προηλθον":["MK6_33","AC12_10"],"εσθιουσιν":["MK7_2","MK7_3","MK7_4","MK7_5","MK7_28","LK5_33","C18_7","C19_13"],"ποτηριων":["MK7_4"],"επερωτωσιν":["MK7_5","RM10_20"],"τηρησητε":["MK7_9","JN15_10"],"συροφοινικισσα":["MK7_26"],"παρεθηκαν":["MK8_6"],"τυφλου":["MK8_23","JN9_32","JN11_37"],"διεβλεψεν":["MK8_25"],"εξεθαμβηθησαν":["MK9_15","MK16_5"],"οδοντας":["MK9_18","AC7_54"],"γενος":["MK9_29","AC7_13","AC7_19","AC17_28","AC17_29","P12_9","RV22_16"],"καθισας":["MK9_35","MK12_41","LK5_3","LK14_28","LK14_31","LK16_6","JN8_2","AC12_21","AC25_6","AC25_17","EP1_20"],"κτισεως":["MK10_6","MK13_19","RM1_20","RM8_19","CL1_15","HB9_11","P23_4","RV3_14"],"προσκολληθησεται":["MK10_7","EP5_31"],"εμπτυσουσιν":["MK10_34"],"αναβλεψω":["MK10_51","LK18_41"],"στηκετε":["MK11_25","C116_13","GL5_1","PP1_27","PP4_1","H13_8","H22_15"],"ητιμασαν":["MK12_4"],"αγωσιν":["MK13_11"],"ενταφιασμον":["MK14_8"],"κεραμιον":["MK14_13","LK22_10"],"ισαι":["MK14_56"],"ευλογητου":["MK14_61"],"προαυλιον":["MK14_68"],"ηρνειτο":["MK14_70"],"γαλιλαιος":["MK14_70","LK22_59","LK23_6","AC5_37"],"επιβαλων":["MK14_72","LK9_62"],"ενδιδυσκουσιν":["MK15_17"],"πορφυραν":["MK15_17","MK15_20","LK16_19"],"καθελειν":["MK15_36"],"κεντυριωνα":["MK15_44"],"νεανισκον":["MK16_5","AC23_18","AC23_22"],"ανθ":["LK1_20","LK12_3","LK19_44","AC12_23","H22_10"],"αφελειν":["LK1_25"],"καθειλεν":["LK1_52"],"ταπεινους":["LK1_52","C27_6"],"αποκριθεισα":["LK1_60"],"απογραφη":["LK2_2"],"ηγεμονευοντος":["LK2_2","LK3_1"],"αγραυλουντες":["LK2_8"],"εσπαργανωμενον":["LK2_12"],"κειμενον":["LK2_12","LK2_16","JN20_7","C13_11"],"λαληθεντων":["LK2_18"],"μητραν":["LK2_23"],"ετος":["LK2_41","LK13_8"],"αναβαινοντων":["LK2_42","JN12_20"],"τελειωσαντων":["LK2_43"],"γνωστοις":["LK2_44"],"ηδειτε":["LK2_49","JN8_19","JN14_7"],"μεταδοτω":["LK3_11"],"πρασσετε":["LK3_13","PP4_9"],"πονηρων":["LK3_19","LK7_21","LK8_2","AC25_18","H23_2","JM2_4"],"βαπτισθεντος":["LK3_21"],"μαθθατ":["LK3_24","LK3_29"],"ναγγαι":["LK3_25"],"αδδι":["LK3_28"],"ελμαδαμ":["LK3_28"],"μελεα":["LK3_31"],"αδαμ":["LK3_38","RM5_14","C115_22","C115_45","T12_13","T12_14","JD1_14"],"στιγμη":["LK4_5"],"πτυξας":["LK4_20"],"εα":["LK4_34"],"εστωτα":["LK5_2","JN20_14","AC4_14","AC7_55","AC7_56","AC22_25","RV10_5","RV19_17"],"επαναγαγειν":["LK5_3"],"ασθενειων":["LK5_15","LK8_2"],"νομοδιδασκαλοι":["LK5_17","T11_7"],"πενθησετε":["LK6_25"],"επληρωσεν":["LK7_1","AC2_2","AC3_18","AC5_3"],"ιαθητω":["LK7_7"],"μαστιγων":["LK7_21","HB11_36"],"θριξιν":["LK7_38","LK7_44","JN11_2","JN12_3"],"αμφοτεροις":["LK7_42"],"καταφιλουσα":["LK7_45"],"τεθεραπευμεναι":["LK8_2"],"σουσαννα":["LK8_3"],"πιστευσαντες":["LK8_12","JN7_39","JN20_29","AC2_44","AC19_2","EP1_13","H22_12","HB4_3"],"λιμνης":["LK8_22"],"αντιπερα":["LK8_26"],"εξεληλυθυιαν":["LK8_46"],"διηπορει":["LK9_7","AC10_17"],"απελθοντι":["LK9_59"],"αναγινωσκεις":["LK10_26","AC8_30"],"πανδοχειον":["LK10_34"],"καθωπλισμενος":["LK11_21"],"γεμει":["LK11_39","RM3_14"],"μυριαδων":["LK12_1","RV5_11","RV9_16"],"εξουσιας":["LK12_11","LK23_7","AC26_12","AC26_18","C19_12","C210_8","EP1_21","EP2_2","EP6_12","CL1_13","CL2_10","CL2_15"],"απολογησησθε":["LK12_11"],"διδαξει":["LK12_12","JN14_26"],"μεριστην":["LK12_14"],"ποιμνιον":["LK12_32","P15_2"],"περιεζωσμεναι":["LK12_35"],"γαμων":["LK12_36","LK16_18"],"ανοιξωσιν":["LK12_36"],"συνεχομαι":["LK12_50","PP1_23"],"πρακτωρ":["LK12_58"],"απαγγελλοντες":["LK13_1"],"μετανοητε":["LK13_3","LK13_5"],"πυργος":["LK13_4"],"ευρισκω":["LK13_7","LK23_4","JN18_38","JN19_4","JN19_6","RM7_21"],"εργαζεσθαι":["LK13_14","JN9_4","C19_6","H14_11","H23_10"],"θεραπευεσθε":["LK13_14"],"ηυξησεν":["LK13_19","AC7_17"],"αγωνιζεσθε":["LK13_24"],"ταπεινων":["LK14_11","LK18_14","C211_7"],"ανταποδοθησεται":["LK14_14","RM11_35"],"μισει":["LK14_26","JN3_20","JN7_7","JN15_18","JN15_19","JN15_23","J13_13"],"ισχυρα":["LK15_14","C11_27","RV18_2","RV18_10"],"ποσοι":["LK15_17"],"σιτευτον":["LK15_23","LK15_27","LK15_30"],"απολωλως":["LK15_24","LK15_32"],"αφαιρειται":["LK16_3"],"εισελθοντι":["LK17_7"],"ανεστησαν":["LK17_12","AC6_9","C110_7"],"αστραπτουσα":["LK17_24"],"επωλουν":["LK17_28"],"εφυτευον":["LK17_28"],"εμπτυσθησεται":["LK18_32"],"παρερχεται":["LK18_37"],"κρινω":["LK19_22","JN5_30","JN8_15","JN8_16","JN12_47","AC7_7","AC15_19"],"αινειν":["LK19_37"],"παρεμβαλουσιν":["LK19_43"],"ειδεναι":["LK20_7","LK22_34","JN14_5","C12_2","C111_3","EP1_18","CL2_1","CL4_6","H14_4","H15_12","TT1_16"],"επερωταν":["LK20_40"],"θετε":["LK21_14"],"απολογηθηναι":["LK21_14"],"συγγενων":["LK21_16","RM9_3"],"αιχμαλωτισθησονται":["LK21_24"],"ηγγιζεν":["LK22_1","AC7_17"],"διαθηκη":["LK22_20","RM11_27","C111_25","HB8_9","HB8_10","HB9_15","HB9_16","HB9_17","HB10_16"],"διεθετο":["LK22_29","AC3_25"],"πινητε":["LK22_30","C111_25","C111_26"],"επιστρεψας":["LK22_32","AC9_40","AC16_18","JM5_20","P22_22","RV1_12"],"υστερησατε":["LK22_35"],"συγκαθισαντων":["LK22_55"],"διαστασης":["LK22_59"],"διαστρεφοντα":["LK23_2"],"ανασειει":["LK23_5"],"ιεροσολυμοις":["LK23_7","JN2_23","JN4_20","JN4_21","JN4_45","JN5_2","JN10_22","AC8_1","AC8_14","AC16_4","AC25_24","AC26_4","AC26_10","AC26_20"],"γινομενον":["LK23_8","JN6_19","AC12_9","AC28_6"],"εχθρα":["LK23_12","RM8_7","JM4_4"],"ανεκραγον":["LK23_18"],"επεκειντο":["LK23_23"],"αιτημα":["LK23_24"],"θυγατερες":["LK23_28","AC2_17","AC21_9"],"πεσετε":["LK23_30","RV6_16"],"ωμιλουν":["LK24_14"],"αγει":["LK24_21","RM2_4"],"διηνοιγεν":["LK24_32"],"αρτου":["LK24_35","JN6_51","AC2_42","C110_17","C111_28"],"πληρωθηναι":["LK24_44","AC1_16"],"ευλογειν":["LK24_51"],"μαρτυρει":["JN1_15","JN3_32","JN5_32","JN5_36","JN8_18","JN10_25","AC22_5","HB10_15"],"στηκει":["JN1_26","RM14_4"],"ιδης":["JN1_33"],"υδριας":["JN2_7"],"κερματα":["JN2_15"],"εληλυθας":["JN3_2","AC21_22"],"επουρανια":["JN3_12","C115_40","HB9_23"],"ζητησις":["JN3_25"],"ελαττουσθαι":["JN3_30"],"μετρου":["JN3_34","C210_13"],"δεδωκεν":["JN3_35","JN5_22","JN5_36","JN6_32","JN6_39","JN7_19","JN7_22","JN10_29","JN12_49","JN18_11","J13_1","J14_13","J15_20"],"χωριου":["JN4_5","AC5_3"],"αληθες":["JN4_18","AC12_9","J12_8","J12_27"],"προσκυνειτε":["JN4_22"],"αληθινος":["JN4_37","JN7_28","J15_20","RV3_7","RV3_14","RV6_10","RV19_11"],"ησθενει":["JN4_46","JN11_2","RM8_3"],"ιασηται":["JN4_47"],"εβραιστι":["JN5_2","JN19_13","JN19_17","JN19_20","JN20_16","RV9_11","RV16_16"],"ιαθεις":["JN5_13"],"ζητω":["JN5_30","JN8_50","C212_14","GL1_10"],"καιομενος":["JN5_35","RV8_10"],"κατεβησαν":["JN6_16","AC8_38","AC14_11","AC14_25","AC16_8"],"συνεισηλθεν":["JN6_22","JN18_15"],"παραδιδοναι":["JN6_71","JN12_4"],"μεμαθηκως":["JN7_15"],"ελληνας":["JN7_35","AC18_4","AC19_10","AC21_28","RM3_9"],"διψα":["JN7_37","RM12_20"],"λιθαζειν":["JN8_5"],"εγραφεν":["JN8_8"],"εμω":["JN8_31","RM3_7","C111_25"],"ελευθερωσει":["JN8_32"],"ηκω":["JN8_42","HB10_7","HB10_9"],"εγνωκατε":["JN8_55","JN14_7","J12_13","J12_14"],"ανεβλεψα":["JN9_11","AC22_13"],"αληθη":["JN10_41","JN19_35","PP4_8","P15_12"],"εξυπνισω":["JN11_11"],"εληλυθεισαν":["JN11_19"],"ειπουσα":["JN11_28","JN20_14"],"πιστευσουσιν":["JN11_48"],"ωφελειτε":["JN12_19"],"ειρηκεν":["JN12_50","AC13_34","C212_9","HB1_13","HB4_3","HB4_4","HB10_9","HB13_5"],"λεντιον":["JN13_4"],"γνωσονται":["JN13_35","AC21_24","RV2_23"],"ταρασσεσθω":["JN14_1","JN14_27"],"παραλημψομαι":["JN14_3"],"ορφανους":["JN14_18","JM1_27"],"γεωργος":["JN15_1","JM5_7"],"αμπελω":["JN15_4"],"μνημονευητε":["JN16_4"],"αγιε":["JN17_11"],"γινωσκη":["JN17_23"],"φανων":["JN18_3"],"κηπω":["JN18_26","JN19_41"],"περιεβαλον":["JN19_2"],"στρατιωτη":["JN19_23","AC28_16"],"συντριβησεται":["JN19_36"],"οθονιοις":["JN19_40"],"πεμπω":["JN20_21"],"ενεγκατε":["JN21_10"],"βαρσαββαν":["AC1_23","AC15_22"],"προσευξαμενοι":["AC1_24","AC6_6","AC13_3","AC14_23","AC21_5"],"πεντηκοστης":["AC2_1","AC20_16","C116_8"],"διαμεριζομεναι":["AC2_3"],"φρυγιαν":["AC2_10","AC16_6","AC18_23"],"απεφθεγξατο":["AC2_14"],"δουλας":["AC2_18"],"ωδινας":["AC2_24"],"οσφυος":["AC2_30","HB7_5"],"εγκατελειφθη":["AC2_31"],"εβασταζετο":["AC3_2"],"βλεψον":["AC3_4"],"εκθαμβοι":["AC3_11"],"εξολεθρευθησεται":["AC3_23"],"σαμουηλ":["AC3_24","AC13_20","HB11_32"],"ποντιος":["AC4_27"],"λαοις":["AC4_27","RV10_11"],"παρακλησεως":["AC4_36","AC13_15","RM15_4","RM15_5","C21_3","C21_4","C21_6","C21_7","C28_4","HB12_5","HB13_22"],"κυπριος":["AC4_36"],"ση":["AC5_4","AC24_4","C18_11","C114_16"],"πραγμα":["AC5_4","C16_1","JM3_16"],"εθεσθε":["AC5_25"],"διακονια":["AC6_1","AC6_4","RM12_7","RM15_31","C23_7","C23_8","C23_9","C26_3","C29_12"],"συνεκινησαν":["AC6_12"],"ψευδεις":["AC6_13","RV2_2"],"μετωκισεν":["AC7_4"],"πατριαρχαι":["AC7_9"],"επισκεψασθαι":["AC7_23"],"υψιστος":["AC7_48"],"στησης":["AC7_60"],"διωγμος":["AC8_1","RM8_35"],"βασιλισσης":["AC8_27"],"ησαιαν":["AC8_28","AC8_30"],"κολληθητι":["AC8_29"],"χειραγωγουντες":["AC9_8"],"πλησθης":["AC9_17"],"ελληνιστας":["AC9_29","AC11_20"],"κορνηλιου":["AC10_17"],"συνομιλων":["AC10_27"],"εργαζομενος":["AC10_35","EP4_28"],"διεκρινοντο":["AC11_2"],"αντιοχειας":["AC11_19","AC11_22","AC14_19"],"μελλειν":["AC11_28","AC19_27","AC24_15","AC25_4","AC27_10","AC28_6"],"εσεσθαι":["AC11_28","AC23_30","AC24_15","AC27_10"],"κοιμωμενος":["AC12_6"],"παυλω":["AC13_7","AC13_43","AC15_2","AC15_22","AC15_25","AC16_9","AC16_17","AC16_29","AC17_2","AC17_4","AC18_9","AC18_12","AC21_4","AC23_16","AC25_9","AC27_3","AC28_16"],"αχλυς":["AC13_11"],"ητησαντο":["AC13_21","AC13_28"],"προσλαλουντες":["AC13_43"],"ευσχημονας":["AC13_50"],"ηλατο":["AC14_10"],"ερμην":["AC14_12","RM16_14"],"διαρρηξαντες":["AC14_14"],"εσυρον":["AC14_19","AC17_6"],"σαμαρειαν":["AC15_3"],"πνικτων":["AC15_29"],"παραδοθεις":["AC15_40"],"τιμοθεος":["AC16_1","AC17_14","AC18_5","AC20_4","RM16_21","C116_10","C21_1","PP1_1","CL1_1","H11_1","H21_1","PM1_1"],"αγοραν":["AC16_19"],"ξυλον":["AC16_24","P12_24","RV18_12","RV22_2","RV22_14"],"ανεθη":["AC16_26"],"σαββατα":["AC17_2"],"υποδεδεκται":["AC17_7"],"ελληνιδων":["AC17_12"],"αγνωστω":["AC17_23"],"νομιζειν":["AC17_29"],"γαλλιωνι":["AC18_17"],"αλεξανδρευς":["AC18_24"],"εσκληρυνοντο":["AC19_9"],"ρωμην":["AC19_21","AC23_11","AC28_14","AC28_16"],"επεσχεν":["AC19_22"],"τεχνιταις":["AC19_24"],"αλεξανδρον":["AC19_33"],"βλασφημουντας":["AC19_37"],"συστροφης":["AC19_40"],"μετριως":["AC20_12"],"ιματισμου":["AC20_33"],"επλεομεν":["AC21_3"],"αποφορτιζομενον":["AC21_3"],"απησπασαμεθα":["AC21_6"],"ενεβημεν":["AC21_6"],"πτολεμαιδα":["AC21_7"],"εντοπιοι":["AC21_12"],"απεδεξαντο":["AC21_17"],"αποστασιαν":["AC21_21"],"προσφορα":["AC21_26","RM15_16","HB10_14","HB10_18"],"αγεσθαι":["AC21_34"],"φυλακιζων":["AC22_19"],"εξεχυννετο":["AC22_20"],"προετειναν":["AC22_25"],"εασαντες":["AC23_32"],"τερτυλλος":["AC24_2"],"παρακαλω":["AC24_4","AC27_34","RM12_1","RM15_30","RM16_17","C11_10","C14_16","C116_15","C22_8","C210_1","EP4_1","PP4_2","T12_1","PM1_9","PM1_10","HB13_19","HB13_22","P12_11","P15_1"],"κινουντα":["AC24_5"],"εκρατησαμεν":["AC24_6"],"διαλεγομενον":["AC24_12"],"εχοιεν":["AC24_19"],"σταντος":["AC24_20"],"κριματος":["AC24_25","HB6_2"],"διετιας":["AC24_27"],"αιτιωματα":["AC25_7"],"επικαλουμαι":["AC25_11","C21_23"],"ποιησαμενος":["AC25_17","HB1_3"],"σεβαστου":["AC25_21"],"ισασιν":["AC26_4"],"προγινωσκοντες":["AC26_5","P23_17"],"μαρτυρομενος":["AC26_22"],"παυλε":["AC26_24","AC27_24"],"ευξαιμην":["AC26_29"],"πρασσει":["AC26_31"],"ιουλιω":["AC27_1"],"πλειν":["AC27_2"],"λυκιας":["AC27_5"],"ενεβιβασεν":["AC27_6"],"υποζωννυντες":["AC27_17"],"αυτοχειρες":["AC27_19"],"πειθαρχησαντας":["AC27_21"],"κεχαρισται":["AC27_24","GL3_18"],"εκπεσειν":["AC27_26","AC27_32"],"προσαγειν":["AC27_27"],"ζευκτηριας":["AC27_40"],"υετον":["AC28_2","HB6_7","JM5_18"],"παρακεχειμακοτι":["AC28_11"],"προεθεμην":["RM1_13"],"ομοιωματι":["RM1_23","RM5_14","RM6_5","RM8_3","PP2_7"],"ασχημοσυνην":["RM1_27","RV16_15"],"αγνοων":["RM2_4","T11_13"],"θυμος":["RM2_8","EP4_31","RV15_1"],"αφρονων":["RM2_20","C211_19","P12_15"],"λογισθησεται":["RM2_26"],"φυσεως":["RM2_27","P21_4"],"παραβατην":["RM2_27","GL2_18"],"εκζητων":["RM3_11"],"ιος":["RM3_13","JM5_3"],"προπατορα":["RM4_1"],"οφειλημα":["RM4_4"],"ασεβη":["RM4_5"],"μακαρισμος":["RM4_9","GL4_15"],"κεκενωται":["RM4_14"],"νενεκρωμενον":["RM4_19"],"καυχωμενοι":["RM5_11","C210_15","PP3_3"],"εβασιλευσεν":["RM5_14","RM5_17","RM5_21","RV19_6"],"δωρεας":["RM5_17","EP4_7","HB6_4"],"γινωσκοντες":["RM6_6","EP5_5","HB10_34","JM1_3","P21_20","P23_3"],"παρεστησατε":["RM6_19"],"σαρκινος":["RM7_14"],"ζητε":["RM8_13"],"ματαιοτητι":["RM8_20","EP4_17"],"συνωδινει":["RM8_22"],"προθεσιν":["RM8_28","EP1_11","EP3_11","T21_9"],"σφαγης":["RM8_36","JM5_5"],"ελευσομαι":["RM9_9","RM15_29","C14_19","C116_5","C212_1","PP2_24"],"βουληματι":["RM9_19"],"προειρηκεν":["RM9_29"],"εκαμψαν":["RM11_4"],"λειμμα":["RM11_5"],"τραπεζα":["RM11_9","HB9_2"],"συγκαμψον":["RM11_10"],"πεσωσιν":["RM11_11"],"κλαδοι":["RM11_16","RM11_19"],"συνεκλεισεν":["RM11_32","GL3_22"],"σωφρονειν":["RM12_3","TT2_6"],"οκνηροι":["RM12_11"],"προνοουμενοι":["RM12_17"],"εκδικουντες":["RM12_19"],"σωρευσεις":["RM12_20"],"λαχανα":["RM14_2"],"λογιζομενω":["RM14_14"],"βρωματι":["RM14_15"],"αρεσκετω":["RM15_2"],"εκοινωνησαν":["RM15_27"],"πληρωματι":["RM15_29"],"αμπλιατον":["RM16_8"],"αριστοβουλου":["RM16_10"],"υπακοη":["RM16_19","C210_6","PM1_21","P11_22"],"ασπαζεται":["RM16_21","RM16_23","C116_19","CL4_10","CL4_12","CL4_14","T24_21","PM1_23","P15_13","J21_13"],"προφητικων":["RM16_26"],"τελους":["C11_8","C21_13","HB3_6","HB3_14","HB6_11","RV2_26"],"χλοης":["C11_11"],"αποδειξει":["C12_4"],"βαθη":["C12_10"],"πνευματικως":["C12_14","RV11_8"],"ανακρινει":["C12_15"],"εποτισεν":["C13_6"],"συνεργοι":["C13_9","C21_24","CL4_11","PM1_24","J31_8"],"συμβασιλευσωμεν":["C14_8"],"εσχατους":["C14_9"],"ιδιαις":["C14_12","EP4_28","H14_11"],"ακουεται":["C15_1"],"επιστολη":["C15_9","C23_2","C23_3","C27_8","CL4_16","H23_17"],"ωφειλετε":["C15_10"],"εξουσιασθησομαι":["C16_12"],"αγαμος":["C17_11","C17_32","C17_34"],"καταλλαγητω":["C17_11"],"διατασσομαι":["C17_17"],"επισπασθω":["C17_18"],"εκληθης":["C17_21","T16_12"],"ευπαρεδρον":["C17_35"],"απερισπαστως":["C17_35"],"περιαγειν":["C19_5"],"αλοωντα":["C19_9","T15_18"],"κενωσει":["C19_15"],"θυουσιν":["C110_20"],"ισχυροτεροι":["C110_22"],"μετεχω":["C110_30"],"κομα":["C111_14","C111_15"],"μεριμνωσιν":["C112_25"],"επεγνωσθην":["C113_12"],"διδοντα":["C114_7","H14_8"],"προφητευειν":["C114_31","C114_39"],"μανθανωσιν":["C114_31"],"ταγματι":["C115_23"],"ηθη":["C115_33"],"ομιλιαι":["C115_33"],"ζωοποιειται":["C115_36"],"χοικος":["C115_47","C115_48"],"εφορεσαμεν":["C115_49"],"κληρονομει":["C115_50"],"κατεποθη":["C115_54"],"περισσευοντες":["C115_58","CL2_7"],"κοπος":["C115_58","H13_5"],"εξουθενηση":["C116_11"],"υποτασσησθε":["C116_16"],"υστερημα":["C116_17","C28_13","C28_14","C211_9","PP2_30"],"σχητε":["C21_15"],"ελαφρια":["C21_17"],"κηρυχθεις":["C21_19"],"αγνοουμεν":["C22_11"],"αρχομεθα":["C23_1"],"εγγεγραμμενη":["C23_2","C23_3"],"απειπαμεθα":["C24_2"],"εγκαταλειπομενοι":["C24_9"],"εκδημουντες":["C25_9"],"πρεσβευομεν":["C25_20"],"καταλλαγητε":["C25_20"],"αδικηθεντος":["C27_12"],"δεδομενην":["C28_1"],"συνεπεμψαμεν":["C28_18","C28_22"],"εδοκιμασαμεν":["C28_22"],"καυχωμαι":["C29_2"],"γενηματα":["C29_10"],"δοξω":["C210_9"],"μετασχηματιζεται":["C211_14"],"νυχθημερον":["C211_25"],"υβρεσιν":["C212_10"],"λοιπας":["C212_13","P23_16"],"καταλαλιαι":["C212_20"],"προημαρτηκοσιν":["C213_2"],"αποτομως":["C213_10","TT1_13"],"ηρεσκον":["GL1_10"],"αφορισας":["GL1_15"],"γαλαται":["GL3_1"],"καταρα":["GL3_13","JM3_10"],"επιδιατασσεται":["GL3_15"],"μορφωθη":["GL4_19"],"φαρμακεια":["GL5_20","RV18_23"],"αγαθωσυνη":["GL5_22","EP5_9"],"οικειους":["GL6_10"],"φυλασσουσιν":["GL6_13"],"πιστοις":["EP1_1","CL1_2","T14_3","T22_2"],"πνευματικη":["EP1_3","CL1_9"],"μεγεθος":["EP1_19"],"πολυποικιλος":["EP3_10"],"υψος":["EP3_18","EP4_8","RV21_16"],"καταντησωμεν":["EP4_13"],"παροργισμω":["EP4_26"],"κενοις":["EP5_6"],"ψαλλοντες":["EP5_19"],"θαλπει":["EP5_29"],"οφθαλμοδουλιαν":["EP6_6"],"ανοιξει":["EP6_19"],"περισσευη":["PP1_9","PP1_26"],"κηρυσσουσιν":["PP1_15"],"καμψη":["PP2_10"],"διεστραμμενης":["PP2_15"],"φρονωμεν":["PP3_15"],"ετερως":["PP3_15"],"αγνα":["PP4_8"],"ορατα":["CL1_16"],"πρωτευων":["CL1_18"],"εορακεν":["CL2_18"],"φυσιουμενος":["CL2_18"],"στοιχειων":["CL2_20"],"βραβευετω":["CL3_15"],"δεξαμενοι":["H11_6"],"βαρει":["H12_7"],"στεγοντες":["H13_1"],"ερωτωμεν":["H14_1","H15_12","H22_1"],"εχουση":["H15_3"],"απεχεσθε":["H15_22"],"ατοπων":["H23_2"],"παιδευθωσιν":["T11_20"],"κοσμιω":["T12_9"],"μανθανετω":["T12_11"],"ηπατηθη":["T12_14"],"εξαπατηθεισα":["T12_14"],"επισκοπον":["T13_2","TT1_7","P12_25"],"αφιλαργυρον":["T13_3"],"ονειδισμον":["T13_7","HB11_26","HB13_13"],"ανεγκλητοι":["T13_10"],"μεταλημψιν":["T14_3"],"γραωδεις":["T14_7"],"επεχε":["T14_16"],"οικειων":["T15_8"],"προκριματος":["T15_21"],"συγκακοπαθησον":["T21_8","T22_3"],"εζητησεν":["T21_17"],"εμπλεκεται":["T22_4"],"συναπεθανομεν":["T22_11"],"εργατην":["T22_15"],"δεσποτη":["T22_21"],"παγιδος":["T22_26"],"βλασφημοι":["T23_2"],"ηρνημενοι":["T23_5"],"ιαμβρης":["T23_8"],"επιφανειαν":["T24_1","T24_8","TT2_13"],"ηγωνισμαι":["T24_7"],"ασπασαι":["T24_19","TT3_15"],"αποστρεφομενων":["TT1_14"],"κοσμωσιν":["TT2_10"],"αυτοκατακριτος":["TT3_11"],"απεχης":["PM1_15"],"πολυτροπως":["HB1_1"],"μετεσχεν":["HB2_14"],"απαλλαξη":["HB2_15"],"ομοιωθηναι":["HB2_17"],"πλειονος":["HB3_3"],"κατασκευασας":["HB3_3","HB3_4"],"σπουδασωμεν":["HB4_11"],"ομνυουσιν":["HB6_16"],"αγκυραν":["HB6_19"],"πηλικος":["HB7_4"],"φυλην":["HB7_14","RV13_7","RV14_6"],"λειτουργος":["HB8_2"],"συντελεσω":["HB8_8"],"διδαξωσιν":["HB8_11"],"λατρειας":["HB9_1","HB9_6"],"κατεσκευασθη":["HB9_2"],"αθετησιν":["HB9_26"],"προσφατον":["HB10_20"],"εκουσιως":["HB10_26","P15_2"],"αποβαλητε":["HB10_35"],"ελπιζομενων":["HB11_1"],"υποστασις":["HB11_1"],"μετετεθη":["HB11_5"],"αλλοτριαν":["HB11_9"],"ορεγονται":["HB11_16"],"προσεφερεν":["HB11_17"],"συγκακουχεισθαι":["HB11_25"],"ιεφθαε":["HB11_32"],"επρισθησαν":["HB11_37"],"προκειμενον":["HB12_1"],"ειρηνικον":["HB12_11"],"επισκοπουντες":["HB12_15","P15_2"],"απεδετο":["HB12_16"],"προστεθηναι":["HB12_19"],"αναθεωρουντες":["HB13_7"],"αναφερωμεν":["HB13_15"],"βραχεων":["HB13_22"],"διασπορα":["JM1_1"],"εξεπεσεν":["JM1_11","P11_24"],"επισκεπτεσθαι":["JM1_27"],"προσωπολημψιαις":["JM2_1"],"διεκριθητε":["JM2_4"],"βρυει":["JM3_11"],"πολεμειτε":["JM4_2"],"ολολυζοντες":["JM5_1"],"εισεληλυθαν":["JM5_4"],"μακροθυμων":["JM5_7"],"πολυσπλαγχνος":["JM5_11"],"ευχεσθε":["JM5_16"],"ιαθητε":["JM5_16","P12_24"],"αποσταλεντι":["P11_12"],"ανυποκριτον":["P11_22"],"οικοδομεισθε":["P12_5"],"επιθυμιων":["P12_11"],"αρκετος":["P14_3"],"οινοφλυγιαις":["P14_3"],"νηψατε":["P14_7","P15_8"],"μεριμναν":["P15_7"],"αδελφοτητι":["P15_9"],"φαινοντι":["P21_19"],"αυχμηρω":["P21_19"],"ταχινην":["P22_1"],"εβασανιζεν":["P22_8"],"απαταις":["P22_13"],"λαιλαπος":["P22_17"],"φθεγγομενοι":["P22_18"],"παροιμιας":["P22_22"],"τηρουμενοι":["P23_7"],"ποταπους":["P23_11"],"ευσεβειαις":["P23_11"],"τετελειωται":["J12_5","J14_17","J14_18"],"αγνιζει":["J13_3"],"γινωσκωμεν":["J15_20"],"απολαβητε":["J21_8"],"γαιω":["J31_1"],"ευχομαι":["J31_2"],"ποιμαινοντες":["JD1_12"],"νεφελαι":["JD1_12"],"πατμω":["RV1_9"],"περγαμον":["RV1_11"],"θυατειρα":["RV1_11"],"καμινω":["RV1_15"],"αδικηθη":["RV2_11"],"ποιαν":["RV3_3"],"μοσχω":["RV4_7"],"ιππος":["RV6_2","RV6_4","RV6_5","RV6_8","RV19_11"],"χοινικες":["RV6_6"],"λευκη":["RV6_11","RV14_14"],"ολυνθους":["RV6_13"],"πετραις":["RV6_16"],"σιγη":["RV8_1"],"εσαλπισεν":["RV8_7","RV8_8","RV8_10","RV8_12","RV9_1","RV9_13","RV11_15"],"σκορπιου":["RV9_5"],"ομοιας":["RV9_10"],"καταβαινοντα":["RV10_1","RV18_1","RV20_1"],"σφραγισον":["RV10_4"],"γραψης":["RV10_4"],"βρεχη":["RV11_6"],"ευφραινονται":["RV11_10"],"διαφθειροντας":["RV11_18"],"δρακων":["RV12_3","RV12_4","RV12_7","RV12_9","RV12_13","RV12_16","RV12_17","RV13_2","RV13_11"],"βλασφημησαι":["RV13_6"],"μετωπον":["RV13_16","RV17_5","RV20_4"],"κιθαριζοντων":["RV14_2"],"ηγορασθησαν":["RV14_4"],"θερισον":["RV14_15"],"χιλιων":["RV14_20"],"τελεσθωσιν":["RV15_8"],"εξεχεαν":["RV16_6"],"ψευδοπροφητου":["RV16_13"],"βασταζοντος":["RV17_7"],"ογδοος":["RV17_11","RV21_20"],"μεμισημενου":["RV18_2"],"πεπωκαν":["RV18_3"],"στρηνιασαντες":["RV18_9"],"οπωρα":["RV18_14"],"πλουτησαντες":["RV18_15"],"φωστηρ":["RV21_11"],"τειχος":["RV21_12","RV21_14","RV21_15","RV21_17"],"επιγεγραμμενα":["RV21_12"],"υαλω":["RV21_18"],"βηρυλλος":["RV21_20"],"αποδιδουν":["RV22_2"],"γεγραμμενας":["RV22_18"]}